LICENCE.txt
MANIFEST.in
README.rst
django-taggin_solving_single_tag_error_issue.diff
setup.py
porticus/__init__.py
porticus/admin.py
porticus/managers.py
porticus/settings.py
porticus/sitemaps.py
porticus/urls.py
porticus/views.py
porticus.egg-info/PKG-INFO
porticus.egg-info/SOURCES.txt
porticus.egg-info/dependency_links.txt
porticus.egg-info/not-zip-safe
porticus.egg-info/requires.txt
porticus.egg-info/top_level.txt
porticus/locale/fr/LC_MESSAGES/django.mo
porticus/locale/fr/LC_MESSAGES/django.po
porticus/migrations/0001_initial.py
porticus/migrations/__init__.py
porticus/models/__init__.py
porticus/models/album.py
porticus/models/gallery.py
porticus/models/ressource.py
porticus/templates/porticus/album_detail.html
porticus/templates/porticus/base.html
porticus/templates/porticus/gallery_detail.html
porticus/templates/porticus/gallery_list.html
porticus/templates/porticus/gallery_tree.html
porticus/templates/porticus/ressource_detail.html
porticus/templates/porticus/tag_detail.html
porticus/templates/porticus/templatetags/album_detail_fragment.html
porticus/templates/porticus/templatetags/gallery_list_fragment.html
porticus/templatetags/__init__.py
porticus/templatetags/porticus_tags.py