Metadata-Version: 1.1
Name: porticus
Version: 2.0.0
Summary: 
